odoo/addons/l10n_fi_payment_reference/README.rst
odoo/addons/l10n_fi_payment_reference/__init__.py
odoo/addons/l10n_fi_payment_reference/__manifest__.py
odoo/addons/l10n_fi_payment_reference/i18n/fi.po
odoo/addons/l10n_fi_payment_reference/i18n/l10n_fi_payment_reference.pot
odoo/addons/l10n_fi_payment_reference/models/__init__.py
odoo/addons/l10n_fi_payment_reference/models/account_invoice.py
odoo/addons/l10n_fi_payment_reference/models/res_company.py
odoo/addons/l10n_fi_payment_reference/models/res_config.py
odoo/addons/l10n_fi_payment_reference/readme/CONFIGURE.rst
odoo/addons/l10n_fi_payment_reference/readme/CONTRIBUTORS.rst
odoo/addons/l10n_fi_payment_reference/readme/DESCRIPTION.rst
odoo/addons/l10n_fi_payment_reference/readme/USAGE.rst
odoo/addons/l10n_fi_payment_reference/static/description/icon.png
odoo/addons/l10n_fi_payment_reference/static/description/index.html
odoo/addons/l10n_fi_payment_reference/tests/__init__.py
odoo/addons/l10n_fi_payment_reference/tests/test_account_invoice.py
odoo/addons/l10n_fi_payment_reference/tests/test_references.py
odoo/addons/l10n_fi_payment_reference/views/account_invoice.xml
odoo/addons/l10n_fi_payment_reference/views/res_config.xml
odoo11_addon_l10n_fi_payment_reference-11.0.1.0.1.dist-info/METADATA
odoo11_addon_l10n_fi_payment_reference-11.0.1.0.1.dist-info/WHEEL
odoo11_addon_l10n_fi_payment_reference-11.0.1.0.1.dist-info/top_level.txt
odoo11_addon_l10n_fi_payment_reference-11.0.1.0.1.dist-info/RECORD
